[
  {
    "id": 203,
    "title": "The Girl with the Dragon Tattoo",
    "author": "Stieg Larsson",
    "genre": "crime",
    "price": 14.99,
    "coverImage": "/images/booksImages (4).jpg",
    "description": "A gripping thriller about a journalist and a hacker investigating a missing person case.",
    "publicationDate": "2005-08-01",
    "ISBN": "978-0307949486",
    "language": "English",
    "pages": 465,
    "publisher": "Norstedts Förlag",
    "quantity": 1,
    "userId": "google-oauth2|117221977605173875699"
  },
  {
    "id": 205,
    "title": "The Catcher in the Rye",
    "author": "J.D. Salinger",
    "genre": "literary",
    "price": 10.49,
    "coverImage": "/images/booksImages (6).jpg",
    "description": "The story of Holden Caulfield, a teenager struggling with alienation and identity in post-war America.",
    "publicationDate": "1951-07-16",
    "ISBN": "978-0316769488",
    "language": "English",
    "pages": 277,
    "publisher": "Little, Brown and Company",
    "quantity": 1,
    "userId": "google-oauth2|117221977605173875699"
  },
  {
    "id": 219,
    "title": "To Kill a Mockingbird",
    "author": "Harper Lee",
    "genre": "historical",
    "price": 10.99,
    "coverImage": "/images/booksImages (1).jpg",
    "description": "A story of racial injustice in the Deep South, as seen through the eyes of a young girl.",
    "publicationDate": "1960-07-11",
    "ISBN": "978-0061120084",
    "language": "English",
    "pages": 324,
    "publisher": "J.B. Lippincott & Co.",
    "stockQuantity": 10,
    "quantity": 10,
    "userId": "google-oauth2|117221977605173875699"
  }
]